pytimeframe/__init__.py
pytimeframe/timeframe.py
pytimeframe-0.0.1.dist-info/WHEEL
pytimeframe-0.0.1.dist-info/RECORD
pytimeframe-0.0.1.dist-info/METADATA
pytimeframe-0.0.1.dist-info/DESCRIPTION.rst
pytimeframe-0.0.1.dist-info/zip-safe
pytimeframe-0.0.1.dist-info/metadata.json
pytimeframe-0.0.1.dist-info/top_level.txt
pytimeframe-0.0.1.dist-info/pbr.json
