Metadata-Version: 2.0
Name: pytimeframe
Version: 0.0.1
Summary: Span date range from time frame string
Home-page: https://github.com/inabhi9/pytimeframe
Author: Abhinav Kotak
Author-email: in.abhi9@gmail.com
License: The MIT License (MIT)
Requires-Dist: pytz
